{
  "release_id": "2026-06-13-launch-readiness-batch-v1",
  "release_name": "Launch readiness batch",
  "description": "Batched local release covering Vercel rate-limit recovery docs, founder evidence readiness, final UX cache freshness, Stitch-aligned brief flow, identity return-path fixes, Sumsub status mapping guards, corridor place intelligence with official-alert handoff into paid briefs, and server-side payment economics gates.",
  "deployment_trigger": "2026-06-13T00:00:00Z-launch-readiness-batch-1",
  "expected_api_function_budget": 12,
  "sumsub_webhook_path": "/api/identity/sumsub-webhook",
  "source_branch": "main",
  "rate_limit_status": "local_batch_hold_until_vercel_window_resets",
  "release_scope": [
    "deployment_recovery",
    "founder_evidence_register",
    "final_ux_cache_freshness",
    "stitch_brief_flow",
    "identity_status_mapping",
    "login_verification_return_paths",
    "corridor_place_intelligence",
    "server_payment_economics_gate"
  ],
  "queued_commit_count": 11,
  "queued_commits": [
    "HEAD Enforce server-side payment economics",
    "bfa2f3e Mark launch readiness batch release",
    "be83ee4 Add corridor place intelligence",
    "ba48675 Preserve return paths through posting verification",
    "18e78d9 Return users to verification after login",
    "2b56c36 Guard Sumsub account status mapping",
    "77ff3d7 Bump final UX theme cache version",
    "738875b Align brief flow with Stitch request UX",
    "3e4229f Add founder evidence register",
    "80bc284 Add deployment state checker",
    "ba6fc03 Document Vercel rate limit recovery"
  ]
}
